smart_money_concepts/__init__.py
smart_money_concepts/cli.py
smart_money_concepts/smc.py
smart_money_concept-0.1.3.dist-info/METADATA
smart_money_concept-0.1.3.dist-info/WHEEL
smart_money_concept-0.1.3.dist-info/entry_points.txt
smart_money_concept-0.1.3.dist-info/top_level.txt
smart_money_concept-0.1.3.dist-info/RECORD
