Metadata-Version: 2.4
Name: smart-money-concept
Version: 0.1.3
Summary: A Python implementation of Smart Money Concepts (SMC) for technical analysis using yfinance data.
Author-email: Prasad <mr.xprasadx@gmail.com>
Project-URL: Homepage, https://github.com/Prasad1612/smart-money-concept
Project-URL: Repository, https://github.com/Prasad1612/smart-money-concept
Project-URL: Issues, https://github.com/Prasad1612/smart-money-concept/issues
Keywords: finance,trading,technical-analysis,smart-money-concepts,yfinance
Classifier: Programming Language :: Python :: 3
Classifier: License :: OSI Approved :: MIT License
Classifier: Operating System :: OS Independent
Classifier: Development Status :: 3 - Alpha
Classifier: Intended Audience :: Developers
Classifier: Topic :: Software Development :: Libraries :: Python Modules
Requires-Python: >=3.8
Requires-Dist: yfinance>=0.2.40
Requires-Dist: pandas>=2.0.0
Requires-Dist: numpy>=1.24.0
Requires-Dist: matplotlib>=3.7.0
